auxiliary/__init__.py
auxiliary/tests.py
auxiliary/utilities.py
krieg/__init__.py
krieg/game.py
krieg/rockpaperscissors.py
krieg/sequential.py
krieg/tictactoe.py
krieg/tests/__init__.py
krieg/tests/test_rockpaperscissors.py
krieg/tests/test_tictactoe.py
krieg/tests/utilities.py
pokerface/__init__.py
pokerface/_actions.py
pokerface/_lookups.py
pokerface/cards.py
pokerface/decks.py
pokerface/evaluators.py
pokerface/factories.py
pokerface/game.py
pokerface/hands.py
pokerface/limits.py
pokerface/ranges.py
pokerface/stages.py
pokerface/stakes.py
pokerface/variants.py
pokerface/tests/__init__.py
pokerface/tests/test_cards.py
pokerface/tests/test_decks.py
pokerface/tests/test_evaluators.py
pokerface/tests/test_game.py
pokerface/tests/test_hands.py
pokerface/tests/test_lookups.py
pokerface/tests/test_ranges.py
pokerface/tests/test_stakes.py
pokerface/tests/test_games/__init__.py
pokerface/tests/test_games/test_badugi.py
pokerface/tests/test_games/test_five_card_draw.py
pokerface/tests/test_games/test_five_card_omaha_hold_em.py
pokerface/tests/test_games/test_greek_hold_em.py
pokerface/tests/test_games/test_kuhn_poker.py
pokerface/tests/test_games/test_omaha_hold_em.py
pokerface/tests/test_games/test_short_deck_hold_em.py
pokerface/tests/test_games/test_single_draw_lowball_27.py
pokerface/tests/test_games/test_six_card_omaha_hold_em.py
pokerface/tests/test_games/test_texas_hold_em.py
pokerface/tests/test_games/test_triple_draw_lowball_27.py
pokerface/tests/test_games/utilities.py
pokerface-1.0.2.dist-info/LICENSE
pokerface-1.0.2.dist-info/METADATA
pokerface-1.0.2.dist-info/WHEEL
pokerface-1.0.2.dist-info/top_level.txt
pokerface-1.0.2.dist-info/RECORD
